antonio2202_sales/sales.py
antonio2202_sales/settings.py
antonio2202_sales-0.0.1.dist-info/METADATA
antonio2202_sales-0.0.1.dist-info/WHEEL
antonio2202_sales-0.0.1.dist-info/RECORD
